Metadata-Version: 2.1
Name: django-cas-nge
Version: 4.3.3
Summary: Django CAS 1.0/2.0/3.0 client authentication library, support Django 2.2, 3.0, 3.1, 3.2, 4.0 and Python 3.7+
Home-page: https://djangocas.dev
Download-URL: https://github.com/tacnaci/django-cas-nge/releases
Author: Joneai
Author-email: mxjoneai@gmail.com
License: BSD
Keywords: django,cas,cas2,cas3,client,sso,single sign-on,Central Authentication Service,authentication,auth
Classifier: Development Status :: 5 - Production/Stable
Classifier: Environment :: Web Environment
Classifier: Framework :: Django
Classifier: Framework :: Django :: 2.2
Classifier: Framework :: Django :: 3.0
Classifier: Framework :: Django :: 3.1
Classifier: Framework :: Django :: 3.2
Classifier: Framework :: Django :: 4.0
Classifier: Intended Audience :: Developers
Classifier: License :: OSI Approved :: MIT License
Classifier: Natural Language :: English
Classifier: Operating System :: OS Independent
Classifier: Programming Language :: Python
Classifier: Programming Language :: Python :: 3
Classifier: Programming Language :: Python :: 3 :: Only
Classifier: Programming Language :: Python :: 3.7
Classifier: Programming Language :: Python :: 3.8
Classifier: Programming Language :: Python :: 3.9
Classifier: Programming Language :: Python :: 3.10
Classifier: Topic :: Internet :: WWW/HTTP
Requires-Python: >=3.7
License-File: LICENSE.txt
